{
  "name": "Simran Manturgimath",
  "title": "Software Developer",
  "email": "simran.rm6@gmail.com",
  "phone": "+1 (703)-389-7074",
  "experience": [
    {
      "title": "Software Developer",
      "company": "EmphaSystem",
      "date": "July 2024 - Present ",
      "responsibilities": [
        " - Contributed to the design and evolution of internal, business-critical web applications used in daily operations.",
        " - Delivered features supporting large datasets, complex workflows, and time-sensitive decision-making.",
        " - Partnered with product and engineering teams to ship reliable improvements to production systems."
      ]
    },
    {
      "title": "Graduate Research Assistant",
      "company": "George Mason University",
      "date": "Feb 2024 - June 2024",
      "responsibilities": [
        " - Conducted research on real-world security breach data and system failure patterns.",
        " - Analyzed experimental results to evaluate detection approaches and reliability concerns.",
        " - Collaborated with research advisors to contribute data-driven insights into system trust and security."
      ]
    },
    {
      "title": "Graduate Professional Assistant",
      "company": "George Mason University",
      "date": "Jan 2023 - Jun 2023",
      "responsibilities": [
        " - Supported graduate recruitment and academic operations for engineering programs.",
        " - Coordinated data, outreach, and events to ensure accurate communication with prospective students.",
        " - Worked closely with faculty and administrative teams to execute recruitment initiatives smoothly."
      ]
    },
    {
      "title": "Software Developer",
      "company": "GB Ventures",
      "date": "Mar 2019 - May 2021",
      "responsibilities": [
        " - Contributed to the development of a multi-tenant web platform supporting business operations.",
        " - Built and evolved features powering high-impact workflows such as payments, requests, and reporting.",
        " - Worked with cross-functional teams as the product scaled in users and complexity."
      ]
    },
    {
      "title": "Web Developer Intern",
      "company": "Cubiccode Digital Media LLP",
      "date": "Jan 2019 - Feb 2019",
      "responsibilities": [
        " - Contributed to the design and delivery of a client-facing website for a small business.",
        " - Worked on improving usability, visual clarity, and content organization for customer-facing pages.",
        " - Supported the launch of a maintainable web presence that enabled ongoing updates and growth."
      ]
    }
  ],
  "education": [
    {
      "degree": "Masters Computer Science | George Mason University",
      "school": "Fairfax, Virginia",
      "date": "Aug 2021 - May 2023",
      "courses": "Analysis of Algorithms, Data Mining, Information and Network Security, Software Specifications and Constructions, System Programming, Machine Learning, Component Based Software Development, Advanced NLP."
    },
    {
      "degree": "Bachelors, Computer Science | KLE MSSCET",
      "school": "Belgaum, India",
      "date": "Jul 2015 - Jul 2019",
      "courses": "Operating Systems, Cloud Computing, Software testing, Object Oriented Programming, Data Structures, DBMS, System programming, Computer Organizations, Unix, Computer Graphics, Microprocessors, Data Communications, Cryptography & Network Security. "
    }
  ],
  "skills": {
    "Languages": ["Javascript", "Typescript", "Python", "Java"],
    "Web Technologies": ["HTML/CSS", "ReactJS", "NodeJS", "Express"],
    "Databases": ["NoSQL", "SQL", "MongoDB", "PostgreSQL"],
    "Cloud": ["AWS (Lambda, S3, EC2, CloudFront)", "Kubernetes"]
  }
}
